{"id":1594120904,"name":"No Time to Explain","icon":"/common/destiny2_content/icons/b4815d2060876f82559502e67bf9c3e3.jpg","watermark":"/common/destiny2_content/icons/0aff1f4463f6f44e9863370ab1ce6983.png","screenshot":"/common/destiny2_content/screenshots/1594120904.jpg","flavor_text":"A single word etched onto the inside of the weapon's casing: Now.","weapon_tier":"exotic","ammo_type":"primary","element_class":"kinetic","weapon_type":"pulse_rifle","powercap":null,"stats":{"impact":33,"zoom":17,"rounds_per_minute":340,"recoil_direction":90,"stability":55,"range":70,"aim_assistance":45,"magazine":24,"reload_speed":60,"inventory_size":57,"handling":42},"frame":{"name":"Rewind Again","description":"Precision shots and shots against combatants slowed or frozen by Stasis will return to the magazine.","icon":"/common/destiny2_content/icons/c4f6be10eeea9ff396131e9206305376.png"},"perks":[[{"stats":{"stability":5,"handling":15},"icon":"/common/destiny2_content/icons/c2a4355c8db7eac12d6dec52d09a20fe.png","description":"Ultra-light barrel. \n  •  Greatly increases handling speed\n  •  Slightly increases stability","id":1840239774,"name":"Fluted Barrel"}],[{"stats":{"range":10},"icon":"/common/destiny2_content/icons/05e357cd152eb0f665ee986aaa3edc56.png","description":"This weapon can fire longer distances.\n  •  Increases range","id":3142289711,"name":"Accurized Rounds"}],[{"stats":{},"icon":"/common/destiny2_content/icons/66f5d4503972122e1fd62e175b0f7b89.png","description":"At 10 stacks of Rewind Again, a small portal will open, shooting bullets from an alternate timeline version of this weapon. Precision hits extend the portal's duration.","id":3556949035,"name":"Time-Slip"}],[{"stats":{},"icon":"/common/destiny2_content/icons/c995638d381d6ff46df5606f49abd7b3.png","description":"Holding down the trigger will fire this weapon at full auto.","id":4267945040,"name":"Full Auto Trigger System"}]]}
