{"id":1641430382,"name":"The Guiding Sight","icon":"/common/destiny2_content/icons/b2aa657b05d7f99edc9045ced825152e.jpg","watermark":"/common/destiny2_content/icons/2347cc2407b51e1debbac020bfcd0224.png","screenshot":"/common/destiny2_content/screenshots/1641430382.jpg","flavor_text":"Forged in honor of Efrideet, and all that inspires.","weapon_tier":"legendary","ammo_type":"primary","element_class":"kinetic","weapon_type":"scout_rifle","powercap":null,"stats":{"impact":67,"zoom":21,"rounds_per_minute":150,"recoil_direction":75,"stability":24,"range":65,"aim_assistance":30,"magazine":13,"reload_speed":36,"inventory_size":40,"handling":27},"frame":{"name":"High-Impact Frame","description":"Slow-firing and high-damage. This weapon is more accurate when stationary and aiming down sights.","icon":"/common/destiny2_content/icons/65fdde950b85bdd1e0383e1016a73661.png"},"perks":[[{"stats":{"handling":-11,"range":12,"zoom":6},"icon":"/common/destiny2_content/icons/c03a51592fe203813f97d0a4e871b450.png","description":"Ranged scope. Long zoom. \n  •  Increases range\n  •  Decreases handling speed","id":679077873,"name":"Rifle Scope ST"},{"stats":{"handling":-3,"range":6,"zoom":5},"icon":"/common/destiny2_content/icons/c03a51592fe203813f97d0a4e871b450.png","description":"Focused scope. Long zoom. \n  •  Slightly increases range\n  •  Slightly decreases handling speed","id":679077872,"name":"Rifle Scope SSF"},{"stats":{"handling":10,"range":5,"zoom":1},"icon":"/common/destiny2_content/icons/43ffd338e67c18c493d164ae7fce1a67.png","description":"Snapshot sight. Short zoom.\n  •  Increases handling speed\n  •  Slightly increases range","id":13792279,"name":"Cleanshot IS"},{"stats":{"range":2,"handling":15},"icon":"/common/destiny2_content/icons/4df80be29a7eb6ba01bf7ea41f46f7da.png","description":"Agile sight. Short zoom. \n  •  Greatly increases handling speed\n  •  Slightly increases range","id":13792278,"name":"Hitmark IS"},{"stats":{"handling":10,"range":6,"zoom":2},"icon":"/common/destiny2_content/icons/ee62caf152c3747675fe43c544d72e45.png","description":"Snapshot sight. Short zoom. \n  •  Slightly increases range\n  •  Increases handling speed","id":2405638015,"name":"Red Dot 2 MOA"},{"stats":{"handling":7,"range":9,"zoom":2},"icon":"/common/destiny2_content/icons/ee62caf152c3747675fe43c544d72e45.png","description":"Agile sight. Short zoom. \n  •  Increases range\n  •  Increases handling speed","id":2405638014,"name":"Red Dot Micro"}],[{"stats":{"magazine":30,"reload_speed":-20},"icon":"/common/destiny2_content/icons/4cd73ae5b1bc1ae0afc7adb34c2f2df6.png","description":"This weapon has a greatly increased magazine size, but reloads much slower.\n  •  Greatly increases magazine size\n  •  Greatly decreases reload speed","id":2420895100,"name":"Extended Mag"},{"stats":{},"icon":"/common/destiny2_content/icons/932e7b84c233c6cc49a58058f8c5144d.png","description":"Faster reloads when the magazine is empty.","id":1431678320,"name":"Alloy Magazine"},{"stats":{"magazine":20},"icon":"/common/destiny2_content/icons/9d8a7be4c2fef471a6fde38d02ab8dae.png","description":"This weapon's magazine is built for higher capacity.\n  •  Increases magazine size","id":1087426260,"name":"Appended Mag"},{"stats":{"range":5},"icon":"/common/destiny2_content/icons/73b724a6839bb3e1db37742f7ed5249b.png","description":"Rounds cause extra damage to combatants' shields and overpenetrate targets. \n  •  Slightly increases range","id":1968497646,"name":"Armor-Piercing Rounds"},{"stats":{"range":5},"icon":"/common/destiny2_content/icons/f06239ee156ee70f99b48e8e1970dbca.png","description":"Shots from this weapon knock the target back farther.\n  •  Slightly increases range","id":1561002382,"name":"High-Caliber Rounds"},{"stats":{"range":5,"stability":10},"icon":"/common/destiny2_content/icons/86e63358fefcb1666160259779594592.png","description":"Rounds ricochet off hard surfaces. \n  •  Increases stability \n  •  Slightly increases range","id":1885400500,"name":"Ricochet Rounds"},{"stats":{"reload_speed":15,"stability":5},"icon":"/common/destiny2_content/icons/ec1bca64fc9709678ea5c297c0e64c19.png","description":"Optimized for fast reloading.\n  •  Slightly increases stability\n  •  Greatly increases reload speed","id":3230963543,"name":"Flared Magwell"},{"stats":{"reload_speed":10,"range":5},"icon":"/common/destiny2_content/icons/1d87312c174b44d5ef1ed24ad42efe9c.png","description":"Improved reload and range.\n  •  Increases reload speed\n  •  Slightly increases range","id":679225683,"name":"Light Mag"}],[{"stats":{},"icon":"/common/destiny2_content/icons/56f26a865c24a6a10cb4177794eb7788.png","description":"Rapid precision hits temporarily increase stability and reload speed.","id":247725512,"name":"Rapid Hit"},{"stats":{},"icon":"/common/destiny2_content/icons/fa7ba2abcd8effd143e287668d7c865b.png","description":"Sliding partially reloads this weapon's magazine and temporarily boosts range and stability.","id":3161816588,"name":"Slideshot"},{"stats":{},"icon":"/common/destiny2_content/icons/b04cf9a75031115055678b71c3c58443.png","description":"This weapon can be drawn unbelievably fast.","id":706527188,"name":"Quickdraw"},{"stats":{},"icon":"/common/destiny2_content/icons/170f957d36cb67001148402abf6a95c6.png","description":"Increases handling, reload speed, and stability for each fully charged ability.","id":3436462433,"name":"Surplus"},{"stats":{},"icon":"/common/destiny2_content/icons/df460693665b7b4dd42f1706e5fbb9e1.png","description":"Overflows the magazine based on the number of rapid kills before reloading.","id":2010801679,"name":"Ambitious Assassin"},{"stats":{},"icon":"/common/destiny2_content/icons/9f3c3ae1bddbed21af1cc6487338028e.png","description":"Increases accuracy, stability, and precision hit targeting when firing from the hip.","id":1866048759,"name":"Hip-Fire Grip"}],[{"stats":{"stability":20,"reload_speed":-30},"icon":"/common/destiny2_content/icons/0070d2be2fa0f2ea5b799c06f29564b8.png","description":"Massively improves weapon stability at the cost of reload speed.","id":11551321,"name":"Iron Grip"},{"stats":{"aim_assistance":20,"range":-30},"icon":"/common/destiny2_content/icons/87a534926730ce32896f53295e655aeb.png","description":"Massively improves weapon target acquisition at the cost of weapon range.","id":4152709778,"name":"Iron Gaze"},{"stats":{},"icon":"/common/destiny2_content/icons/6f82df3f2505654c266d2ee34c2a922d.png","description":"Increased damage against bosses, vehicles, and Guardians with their Super active.","id":1546637391,"name":"Vorpal Weapon"},{"stats":{},"icon":"/common/destiny2_content/icons/b7106e2123d59e57a1547bc006892ebc.png","description":"Hitting three separate targets increases damage for a moderate duration.","id":4049631843,"name":"One for All"},{"stats":{},"icon":"/common/destiny2_content/icons/00d3a72dbd506749ccddb050c9312977.png","description":"Using your grenade ability changes this weapon's damage type to match your subclass until you stow it.","id":1774574192,"name":"Osmosis"},{"stats":{},"icon":"/common/destiny2_content/icons/49958f356ea1df930888d15fe6539fe1.png","description":"Causing damage with this weapon increases its stability.","id":2387244414,"name":"Zen Moment"}]]}
