{"id":2782325300,"name":"Quickfang","icon":"/common/destiny2_content/icons/87284b1d8453c9b137a0c4a37c10202a.jpg","watermark":"/common/destiny2_content/icons/b07d89064a1fc9a8e061f59b7c747fa5.png","screenshot":"/common/destiny2_content/screenshots/2782325300.jpg","flavor_text":"My smile is full of blades.","weapon_tier":"legendary","ammo_type":"heavy","element_class":"void","weapon_type":"sword","powercap":null,"stats":{"swing_speed":80,"impact":60,"charge_rate":20,"guard_resistance":0,"guard_efficiency":0,"ammo_capacity":74,"inventory_size":0,"zoom":0},"frame":{"name":"Lightweight Frame","description":"[Heavy Attack]  : Launch a heavy dash attack.\nHeavy attacks are stronger with full energy.","icon":"/common/destiny2_content/icons/530b400d5cec3bf6aca7c5efc46fea20.png"},"perks":[[{"stats":{"magazine":20,"ammo_capacity":20},"icon":"/common/destiny2_content/icons/524e24197c0e4d2c5a73f29e3a28e19b.png","description":"Increased sword ammo.","id":436053704,"name":"Hungry Edge"},{"stats":{"magazine":35,"impact":-5,"ammo_capacity":35},"icon":"/common/destiny2_content/icons/195157f00f406f7203052418ae0ff5d0.png","description":"Greatly increased sword ammo at the cost of damage.","id":1261178282,"name":"Enduring Blade"},{"stats":{"impact":5},"icon":"/common/destiny2_content/icons/bf4e60b9b3289fb9d2c3ffa0e4c2cc04.png","description":"Increased sword damage.","id":2827049491,"name":"Honed Edge"},{"stats":{"magazine":-20,"impact":10,"ammo_capacity":-20},"icon":"/common/destiny2_content/icons/464c494e9ac760699272764a9929eff0.png","description":"Increased damage at the cost of sword ammo.","id":3666208348,"name":"Jagged Edge"},{"stats":{"magazine":10,"impact":3,"ammo_capacity":10},"icon":"/common/destiny2_content/icons/f4366b8df3efab997683662dfedc012a.png","description":"Increased sword damage and ammo.","id":938542991,"name":"Tempered Edge"}],[{"stats":{"charge_time":10,"guard_resistance":20,"guard_endurance":50,"inventory_size":50,"stability":20,"charge_rate":10,"guard_efficiency":30},"icon":"/common/destiny2_content/icons/7c04ae7d23ee842c2b58c3e9c0f5855f.png","description":"Sword Guard has low overall defenses, but increases charge rate.","id":269888150,"name":"Swordmaster's Guard"}],[{"stats":{},"icon":"/common/destiny2_content/icons/8d005d05d75b57fe0a78e2aa68519e68.png","description":"Sword ammo granted for every other powered sword kill.","id":2590710093,"name":"Tireless Blade"},{"stats":{},"icon":"/common/destiny2_content/icons/0619b0257fec929e5b6eeb5890c99c53.png","description":"[Light Attack]  : Landing three light-attack hits within a short time grants Sword ammo.","id":1749209109,"name":"Relentless Strikes"},{"stats":{},"icon":"/common/destiny2_content/icons/8a42d3e3d7b4c1c38755f5e0ac186f0b.png","description":"Guarding while receiving damage generates class ability energy.","id":2030760728,"name":"Energy Transfer"},{"stats":{},"icon":"/common/destiny2_content/icons/8ec196e722bd127d214e47efb82ba9bf.png","description":"Killing combatants with this weapon generates a small amount of Super energy.","id":2726471870,"name":"Thresh"}],[{"stats":{},"icon":"/common/destiny2_content/icons/e190dc87349887b6f585ede0f2a73356.png","description":"Sword Kills boost movement speed and damage.","id":354401740,"name":"Assassin's Blade"},{"stats":{},"icon":"/common/destiny2_content/icons/96aac853bf520635d09558f589abeade.png","description":"Quick attacks immediately after swapping to this sword do additional damage.","id":1685431615,"name":"En Garde"},{"stats":{},"icon":"/common/destiny2_content/icons/a9170ded6471b4afd2d8218ccddd644e.png","description":"Melee blocked immediately after guarding disorients and weakens the attacker.","id":2244851822,"name":"Flash Counter"},{"stats":{},"icon":"/common/destiny2_content/icons/b7106e2123d59e57a1547bc006892ebc.png","description":"Hitting three separate targets increases damage for a moderate duration.","id":4049631843,"name":"One for All"}]]}
